btok/__init__.py
btok/categorizer.py
btok/constants.py
btok/simplify.py
btok/tokenizer.py
btok/utils.py
btok-0.3.dist-info/licenses/LICENSE
btok-0.3.dist-info/METADATA
btok-0.3.dist-info/WHEEL
btok-0.3.dist-info/top_level.txt
btok-0.3.dist-info/RECORD
