Metadata-Version: 2.4
Name: btok
Version: 0.3
Summary: A Python tokenizer trained on modern web corpus
Author: Hansimov
Project-URL: Homepage, https://github.com/Hansimov/btok
Project-URL: Issues, https://github.com/Hansimov/btok/issues
Classifier: Programming Language :: Python :: 3
Classifier: License :: OSI Approved :: MIT License
Classifier: Operating System :: OS Independent
Requires-Python: >=3.6
License-File: LICENSE
Requires-Dist: tclogger
Requires-Dist: sentencepiece
Dynamic: license-file
